README.md
setup.py
Paramo.egg-info/PKG-INFO
Paramo.egg-info/SOURCES.txt
Paramo.egg-info/dependency_links.txt
Paramo.egg-info/top_level.txt
paramo/__init__.py
paramo/parse.py
paramo/util.py