Metadata-Version: 2.1
Name: Paramo
Version: 1.0.0
Summary: Better HTTP parameters.
Home-page: https://github.com/ZSendokame/Paramo
Author: ZSendokame
License: MIT license
Platform: UNKNOWN
Classifier: Environment :: Web Environment
Classifier: Intended Audience :: Developers
